{"paths":{"0":["config/launch",0],"4":["i18n.string/zh",0],"8":["i18n.string/en",0]},"types":["cc.JsonAsset"],"uuids":["00Jj5IR9dBOLiNx+0eGkIC","71VhFCTINJM6/Ky3oX9nBT","99FwsL0hBG8bITfZ4/IwmK","b4P/PCArtIdIH38t6mlw8Y","cf0p/nPBdLHL8/S5v+pltn","cf73jxyN9Jt47QTJU6ziYh","db4gUnu3hBbImZxxAtqaCJ","e8Ueib+qJEhL6mXAHdnwbi","fbDH8cNqpJz6JAFoaNCfqZ","02delMVqdBD70a/HSD99FK","29FYIk+N1GYaeWH/q1NxQO","675ovJ2tVK2aLYfgPUWOMv","8855/VlrRKd6H0MSRnFxAU","a2MjXRFdtLlYQ5ouAFv/+R","e97GVMl6JHh5Ml5qEDdSGa","ecpdLyjvZBwrvm+cedCcQy","f0BIwQ8D5Ml7nTNQbh1YlS"],"scenes":{"db://assets/resources/scene/load.fire":6},"redirect":[9,0,15,0],"deps":["internal"],"packs":{"088488c03":[1,2,3,5,7],"0ee7bab8d":[10,11,12,13,6,14,16]},"name":"resources","importBase":"import","nativeBase":"native","debug":false,"isZip":false,"encrypted":false,"versions":{"import":[0,"90552","088488c03","d00d1","0ee7bab8d","fca57",4,"460e1",8,"7d7a2"],"native":[1,"c06a9",2,"d1118",3,"83fcc",5,"a4b59",7,"90cf4"]}}